{
  "page": "guides/ships/dossiers/corsair-ax.html",
  "lead": [
    "Figures on this page are verified against the sources below."
  ],
  "sources": [
    {
      "label": "Coriolis",
      "what": "Interactive outfitting &amp; build planner, preloaded for this ship &mdash; used to validate the AX loadout, Gauss capacitor budget and the Guardian-reinforcement plan across the optionals.",
      "url": "https://coriolis.io/outfit/imperial_corsair",
      "display": "coriolis.io/outfit/imperial_corsair"
    },
    {
      "label": "EDCD coriolis-data",
      "what": "Ship slot layout, hardpoint sizes and the absence of military slots behind this AX reinforcement plan.",
      "url": "https://github.com/EDCD/coriolis-data/blob/master/ships/imperial_corsair.json",
      "display": "coriolis-data/ships/imperial_corsair.json"
    },
    {
      "label": "Inara — Corsair",
      "what": "Stock hull stats, hardpoint/internal layout, utility-mount count and price used for the AX cost figures.",
      "url": "https://inara.cz/elite/ship/44/",
      "display": "inara.cz/elite/ship/44"
    },
    {
      "label": "Fandom — Corsair",
      "what": "Manufacturer (Gutamaya) and hull profile, cross-referenced against AX weapon class limits (no huge or military mounts).",
      "url": "https://elite-dangerous.fandom.com/wiki/Corsair",
      "display": "elite-dangerous.fandom.com/wiki/Corsair"
    },
    {
      "label": "Elite Dangerous (official)",
      "what": "Frontier's official Corsair ship page &mdash; manufacturer specs, feature overview, and the ship render used on this page.",
      "url": "https://www.elitedangerous.com/equipment/starships/corsair",
      "display": "elitedangerous.com/.../corsair"
    }
  ]
}
