{
  "page": "guides/ships/dossiers/imperial-courier-multipurpose.html",
  "lead": [
    "Figures on this page are verified against the sources below."
  ],
  "sources": [
    {
      "label": "Coriolis",
      "what": "Interactive outfitting &amp; build planner used to validate the multirole slot fit, cargo and jump figures for this ship.",
      "url": "https://coriolis.io/outfit/imperial_courier",
      "display": "coriolis.io/outfit/imperial_courier"
    },
    {
      "label": "Elite Dangerous (official)",
      "what": "Frontier's official Imperial Courier ship page — manufacturer specs, feature overview, and the ship render used on this page.",
      "url": "https://www.elitedangerous.com/equipment/starships/imperial-courier",
      "display": "elitedangerous.com/.../imperial-courier"
    },
    {
      "label": "EDCD coriolis-data",
      "what": "Hardpoint sizes, optional-internal slot layout and engineering blueprint data behind the loadout and peer tables.",
      "url": "https://github.com/EDCD/coriolis-data/blob/master/ships/imperial_courier.json",
      "display": "coriolis-data/ships/imperial_courier.json"
    },
    {
      "label": "Inara &mdash; Imperial Courier",
      "what": "Ship reference page cross-checked for hull stats, module slot layout and the Imperial Master rank requirement.",
      "url": "https://inara.cz/elite/ship/32/",
      "display": "inara.cz/elite/ship/32"
    },
    {
      "label": "Fandom wiki",
      "what": "Imperial Courier ship article: role profile, Gutamaya manufacture, and rank gating backing the write-up.",
      "url": "https://elite-dangerous.fandom.com/wiki/Imperial_Courier",
      "display": "fandom.com/wiki/Imperial_Courier"
    }
  ]
}
