{
  "page": "guides/ships/ship-dossiers/type-9-heavy-passenger.html",
  "lead": [
    "Figures on this page are verified against the sources below."
  ],
  "sources": [
    {
      "label": "Coriolis",
      "what": "Interactive outfitting &amp; build planner, preloaded for this ship.",
      "url": "https://coriolis.io/outfit/type_9_heavy",
      "display": "coriolis.io/outfit/type_9_heavy"
    },
    {
      "label": "EDSY",
      "what": "Alternate outfitting planner used to cross-check slot sizes and engineered module figures.",
      "url": "https://edsy.org/#/L=I-",
      "display": "edsy.org"
    },
    {
      "label": "Elite Dangerous (official)",
      "what": "Frontier's official Type-9 Heavy ship page — manufacturer specs, feature overview, and the ship render used on this page.",
      "url": "https://www.elitedangerous.com/equipment/starships/type-9-heavy",
      "display": "elitedangerous.com/.../type-9-heavy"
    },
    {
      "label": "EDCD coriolis-data",
      "what": "Ship slot layout, passenger-cabin sizing, and engineering blueprint data.",
      "url": "https://github.com/EDCD/coriolis-data/blob/master/ships/type_9_heavy.json",
      "display": "coriolis-data/ships/type_9_heavy.json"
    },
    {
      "label": "Inara &mdash; Type-9 Heavy",
      "what": "Ship specification, base stats, and shipyard pricing for this hull.",
      "url": "https://inara.cz/elite/ship/65/",
      "display": "inara.cz/elite/ship/65"
    },
    {
      "label": "ED Wiki &mdash; Type-9 Heavy",
      "what": "Hull role, manufacturer background, and hardpoint / internal layout.",
      "url": "https://elite-dangerous.fandom.com/wiki/Type-9_Heavy",
      "display": "elite-dangerous.fandom.com/wiki/Type-9_Heavy"
    }
  ]
}
