{
  "page": "guides/ships/best-ships-by-role/mining.html",
  "lead": [
    "Figures on this page are verified against the sources below."
  ],
  "sources": [
    {
      "label": "EDCD coriolis-data",
      "what": "Ship slot layout, module variants, and engineering blueprint data.",
      "url": "https://github.com/EDCD/coriolis-data/tree/master/ships",
      "display": "coriolis-data/ships/"
    },
    {
      "label": "Inara",
      "what": "Commodity database &mdash; mineral prices and demand that set the credits-per-ton value of each hull&rsquo;s cargo.",
      "url": "https://inara.cz/elite/commodities/",
      "display": "inara.cz/elite/commodities"
    },
    {
      "label": "ED Wiki &mdash; Miner",
      "what": "Mining career mechanics (laser, core, sub-surface) the suitability ratings weigh.",
      "url": "https://elite-dangerous.fandom.com/wiki/Miner",
      "display": "elite-dangerous.fandom.com/wiki/Miner"
    },
    {
      "label": "ED Wiki &mdash; Mining Laser",
      "what": "Mining tool and limpet-controller requirements that decide effective cargo per hull.",
      "url": "https://elite-dangerous.fandom.com/wiki/Mining_Laser",
      "display": "elite-dangerous.fandom.com/wiki/Mining_Laser"
    },
    {
      "label": "YouTube — The Buur Pit",
      "what": "Review of the Type-11 Prospector, weighing the dedicated mining hull directly against established laser-mining setups.",
      "url": "https://www.youtube.com/watch?v=S5DVPOoAZjc",
      "display": "youtube.com/watch?v=S5DVPOoAZjc"
    },
    {
      "label": "YouTube — Mile 13 Gaming",
      "what": "Hands-on test of the Type-11 Prospector, the game's first purpose-built mining ship, in the field.",
      "url": "https://www.youtube.com/watch?v=5OJx3kGYd60",
      "display": "youtube.com/watch?v=5OJx3kGYd60"
    },
    {
      "label": "YouTube — TheYamiks",
      "what": "Opinionated review of the Type-11 Prospector, Elite's first dedicated mining vessel, against general-purpose miners.",
      "url": "https://www.youtube.com/watch?v=PO4jjYwqTVI",
      "display": "youtube.com/watch?v=PO4jjYwqTVI"
    }
  ]
}
